{
    "name": "secdeva/cardTypes/securityIssue",
    "workflow": "secdeva/workflows/securityIssue",
    "customFields": [
        {
            "name": "secdeva/fieldTypes/securityIssueCategory",
            "isCalculated": false
        },
        {
            "name": "secdeva/fieldTypes/severity",
            "isCalculated": false
        },
        {
            "name": "secdeva/fieldTypes/severityJustification",
            "isCalculated": false
        },
        {
            "name": "secdeva/fieldTypes/rootCauseCategory",
            "isCalculated": false
        },
        {
            "name": "secdeva/fieldTypes/rootCauseJustification",
            "isCalculated": false
        },
        {
            "name": "secdeva/fieldTypes/strategy",
            "isCalculated": false
        },
        {
            "name": "secdeva/fieldTypes/reporting",
            "isCalculated": false
        },
        {
            "name": "secdeva/fieldTypes/testingToBypassMitigation",
            "isCalculated": false
        }
    ],
    "alwaysVisibleFields": [
        "secdeva/fieldTypes/securityIssueCategory",
        "secdeva/fieldTypes/severity",
        "secdeva/fieldTypes/severityJustification",
        "secdeva/fieldTypes/rootCauseCategory",
        "secdeva/fieldTypes/rootCauseJustification",
        "secdeva/fieldTypes/strategy",
        "secdeva/fieldTypes/reporting",
        "secdeva/fieldTypes/testingToBypassMitigation"
    ],
    "optionallyVisibleFields": [],
    "displayName": "Security issue",
    "description": "A security-related issue such as a vulnerability or threat"
}